ncplot/__init__.py
ncplot/command_line.py
ncplot/deprecated.py
ncplot/plot.py
ncplot/utils.py
ncplot/xarray.py
ncplot-0.3.10.dist-info/LICENSE
ncplot-0.3.10.dist-info/METADATA
ncplot-0.3.10.dist-info/WHEEL
ncplot-0.3.10.dist-info/entry_points.txt
ncplot-0.3.10.dist-info/top_level.txt
ncplot-0.3.10.dist-info/RECORD
