Metadata-Version: 2.1
Name: ncplot
Version: 0.3.10
Summary: Interactive viewing of NetCDF data
Home-page: https://github.com/pmlmodelling/ncplot
Author: Robert Wilson
Author-email: rwi@pml.ac.uk
Maintainer: Robert Wilson
Project-URL: Bug Tracker, https://github.com/pmlmodelling/ncplot/issues
Project-URL: Documentation, https://ncplot.readthedocs.io/en/stable
Project-URL: Source Code, https://github.com/pmlmodelling/ncplot
Classifier: License :: OSI Approved :: GNU General Public License v3 (GPLv3)
Classifier: Programming Language :: Python :: 3.8
Classifier: Programming Language :: Python :: 3.9
Classifier: Programming Language :: Python :: 3.10
Classifier: Programming Language :: Python :: 3.11
Classifier: Programming Language :: Python :: 3.12
Requires-Python: >=3.6.1
License-File: LICENSE
Requires-Dist: numpy
Requires-Dist: xarray
Requires-Dist: netCDF4
Requires-Dist: hvplot
Requires-Dist: holoviews
Requires-Dist: bokeh
Requires-Dist: panel
Requires-Dist: pandas
Requires-Dist: metpy
Requires-Dist: jupyter-bokeh
Requires-Dist: datashader ; python_version <= "3.10"
Provides-Extra: complete
Requires-Dist: geoviews ; extra == 'complete'
